NeuroFlex/NeuroFlex.py
NeuroFlex/__init__.py
NeuroFlex/constants.py
NeuroFlex/main.py
NeuroFlex/model_monitoring.py
NeuroFlex/neuroflex_integration.py
NeuroFlex/threat_detection.py
NeuroFlex/Dojo/__init__.py
NeuroFlex/Dojo/custom_model.py
NeuroFlex/Dojo/dojo_framework.py
NeuroFlex/Dojo/test_advanced_features.py
NeuroFlex/Dojo/test_bayesian_inference.py
NeuroFlex/Dojo/test_connectionist_models.py
NeuroFlex/Dojo/test_error_handling.py
NeuroFlex/Dojo/test_self_management.py
NeuroFlex/Dojo/test_situated_cognition.py
NeuroFlex/Dojo/test_standalone_model.py
NeuroFlex/Prompt_Agent/__init__.py
NeuroFlex/Prompt_Agent/agentic_behavior.py
NeuroFlex/Transformers/__init__.py
NeuroFlex/Transformers/unified_transformer.py
NeuroFlex/advanced_models/__init__.py
NeuroFlex/advanced_models/advanced_math_solving.py
NeuroFlex/advanced_models/advanced_time_series_analysis.py
NeuroFlex/advanced_models/multi_modal_learning.py
NeuroFlex/ai_ethics/__init__.py
NeuroFlex/ai_ethics/advanced_security_agent.py
NeuroFlex/ai_ethics/aif360_integration.py
NeuroFlex/ai_ethics/ethical_framework.py
NeuroFlex/ai_ethics/explainable_ai.py
NeuroFlex/ai_ethics/rl_module.py
NeuroFlex/ai_ethics/scikit_bio_integration.py
NeuroFlex/ai_ethics/self_fixing_algorithms.py
NeuroFlex/bci_integration/__init__.py
NeuroFlex/bci_integration/bci_processing.py
NeuroFlex/bci_integration/neunets_integration.py
NeuroFlex/bci_integration/neuro_data_integration.py
NeuroFlex/bci_integration/neuroscience_models.py
NeuroFlex/bci_integration/real_time_feedback.py
NeuroFlex/cognitive_architectures/__init__.py
NeuroFlex/cognitive_architectures/advanced_thinking.py
NeuroFlex/cognitive_architectures/cognitive_architecture.py
NeuroFlex/cognitive_architectures/consciousness_simulation.py
NeuroFlex/cognitive_architectures/custom_cognitive_model.py
NeuroFlex/cognitive_architectures/extended_cognitive_architectures.py
NeuroFlex/config/__init__.py
NeuroFlex/config/config.py
NeuroFlex/config/logging_config.py
neuroflex-0.1.4.dist-info/LICENSE
neuroflex-0.1.4.dist-info/METADATA
neuroflex-0.1.4.dist-info/WHEEL
neuroflex-0.1.4.dist-info/top_level.txt
neuroflex-0.1.4.dist-info/RECORD
