Metadata-Version: 2.1
Name: neuroflex
Version: 0.1.4
Summary: An advanced neural network framework with interpretability, generalization, robustness, and fairness features
Home-page: https://github.com/VishwamAI/neuroflex
Author: kasinadhsarma
Author-email: kasinadhsarma@gmail.com
Classifier: Development Status :: 3 - Alpha
Classifier: Intended Audience :: Developers
Classifier: Intended Audience :: Science/Research
Classifier: License :: OSI Approved :: MIT License
Classifier: Programming Language :: Python :: 3
Classifier: Programming Language :: Python :: 3.8
Classifier: Programming Language :: Python :: 3.9
Classifier: Programming Language :: Python :: 3.10
Classifier: Programming Language :: Python :: 3.11
Classifier: Programming Language :: Python :: 3.12
Classifier: Topic :: Scientific/Engineering :: Artificial Intelligence
Requires-Python: >=3.8
License-File: LICENSE
Requires-Dist: absl-py
Requires-Dist: adversarial-robustness-toolbox
Requires-Dist: aiohappyeyeballs
Requires-Dist: aiohttp
Requires-Dist: aiosignal
Requires-Dist: alphafold
Requires-Dist: appdirs
Requires-Dist: astunparse
Requires-Dist: attrs
Requires-Dist: autograd
Requires-Dist: autoray
Requires-Dist: biom-format
Requires-Dist: biopython (==1.80)
Requires-Dist: blosc2
Requires-Dist: cachetools
Requires-Dist: certifi
Requires-Dist: charset-normalizer
Requires-Dist: chex (==0.1.6)
Requires-Dist: CHSPy
Requires-Dist: click (==8.0.4)
Requires-Dist: contextlib2
Requires-Dist: deap
Requires-Dist: decorator
Requires-Dist: dill
Requires-Dist: dm-haiku (==0.0.9)
Requires-Dist: dm-sonnet
Requires-Dist: dm-tree
Requires-Dist: docker
Requires-Dist: dpath
Requires-Dist: ete3
Requires-Dist: etils
Requires-Dist: filelock
Requires-Dist: flatbuffers
Requires-Dist: flax (==0.6.10)
Requires-Dist: frozenlist
Requires-Dist: fsspec
Requires-Dist: gast (<=0.4.0,>=0.2.1)
Requires-Dist: google-pasta
Requires-Dist: grpcio
Requires-Dist: gym
Requires-Dist: h5py
Requires-Dist: huggingface-hub
Requires-Dist: humanize
Requires-Dist: idna
Requires-Dist: immutabledict
Requires-Dist: importlib-resources
Requires-Dist: iniconfig
Requires-Dist: jax (==0.4.13)
Requires-Dist: jaxlib (==0.4.13)
Requires-Dist: Jinja2
Requires-Dist: jitcdde
Requires-Dist: jitcxde-common
Requires-Dist: jmp
Requires-Dist: joblib
Requires-Dist: keras (<2.13,>=2.12.0)
Requires-Dist: lale (==0.6.0)
Requires-Dist: libclang
Requires-Dist: lightning-utilities
Requires-Dist: llvmlite
Requires-Dist: Markdown
Requires-Dist: markdown-it-py
Requires-Dist: MarkupSafe
Requires-Dist: mdurl
Requires-Dist: ml-collections
Requires-Dist: ml-dtypes
Requires-Dist: mpmath
Requires-Dist: msgpack
Requires-Dist: multidict
Requires-Dist: namex
Requires-Dist: natsort
Requires-Dist: ndindex
Requires-Dist: nest-asyncio
Requires-Dist: networkx
Requires-Dist: neurolib
Requires-Dist: numba
Requires-Dist: numexpr
Requires-Dist: numpy (==1.23.5)
Requires-Dist: nvidia-cublas-cu11
Requires-Dist: nvidia-cuda-cupti-cu11
Requires-Dist: nvidia-cuda-nvrtc-cu11
Requires-Dist: nvidia-cuda-runtime-cu11
Requires-Dist: nvidia-cudnn-cu11
Requires-Dist: nvidia-cufft-cu11
Requires-Dist: nvidia-curand-cu11
Requires-Dist: nvidia-cusolver-cu11
Requires-Dist: nvidia-cusparse-cu11
Requires-Dist: nvidia-nccl-cu11
Requires-Dist: nvidia-nvtx-cu11
Requires-Dist: openmm (==8.1.1)
Requires-Dist: opt-einsum
Requires-Dist: optax (==0.1.5)
Requires-Dist: optree
Requires-Dist: orbax-checkpoint (==0.2.1)
Requires-Dist: packaging
Requires-Dist: pandas
Requires-Dist: patsy
Requires-Dist: pbr
Requires-Dist: PennyLane (==0.30.0)
Requires-Dist: PennyLane-Lightning (==0.30.0)
Requires-Dist: pluggy
Requires-Dist: protobuf (==3.20.3)
Requires-Dist: psutil
Requires-Dist: py-cpuinfo
Requires-Dist: Pygments
Requires-Dist: pypet
Requires-Dist: pytest
Requires-Dist: python-dateutil
Requires-Dist: pytorch-lightning (==1.9.5)
Requires-Dist: pytz
Requires-Dist: PyYAML
Requires-Dist: qiskit (>=1.0.0)
Requires-Dist: qiskit-aer (>=0.12.0)
Requires-Dist: qiskit-algorithms (>=0.2.0)
Requires-Dist: regex
Requires-Dist: requests
Requires-Dist: rich
Requires-Dist: rustworkx (>=0.13.0)
Requires-Dist: safetensors
Requires-Dist: scikit-bio (<0.6.0,>=0.5.8)
Requires-Dist: scikit-learn (==1.1.1)
Requires-Dist: scipy (==1.9.0)
Requires-Dist: six
Requires-Dist: statsmodels
Requires-Dist: stevedore
Requires-Dist: symengine
Requires-Dist: sympy
Requires-Dist: tables
Requires-Dist: tabulate
Requires-Dist: tensorboard (<2.13,>=2.12)
Requires-Dist: tensorboard-data-server
Requires-Dist: tensorflow (==2.12.0)
Requires-Dist: tensorflow-io-gcs-filesystem
Requires-Dist: tensorstore
Requires-Dist: termcolor
Requires-Dist: threadpoolctl
Requires-Dist: tokenizers (==0.13.3)
Requires-Dist: toml
Requires-Dist: toolz
Requires-Dist: torch (==1.13.1)
Requires-Dist: torchmetrics
Requires-Dist: torchvision (==0.14.1)
Requires-Dist: tqdm
Requires-Dist: transformers (==4.30.2)
Requires-Dist: triton (==2.0.0)
Requires-Dist: typing-extensions (<4.6.0,>=3.7.4)
Requires-Dist: tzdata
Requires-Dist: urllib3
Requires-Dist: Werkzeug
Requires-Dist: wrapt
Requires-Dist: xarray
Requires-Dist: yarl
Requires-Dist: zipp
Requires-Dist: PyQt5
Requires-Dist: einops
Requires-Dist: prophet
Requires-Dist: aif360
Requires-Dist: PyWavelets
Requires-Dist: filterpy
Provides-Extra: dev
Requires-Dist: pytest ; extra == 'dev'
Requires-Dist: flake8 ; extra == 'dev'
